mkdocs_graph_plugin/__init__.py
mkdocs_graph_plugin/_version.py
mkdocs_graph_plugin/graph.py
mkdocs_graph_plugin/plugin.py
mkdocs_graph_plugin/static/graph.css
mkdocs_graph_plugin/static/graph.js
mkdocs_graph_plugin-1.2.1.post1.dev0.dist-info/licenses/LICENSE
mkdocs_graph_plugin-1.2.1.post1.dev0.dist-info/METADATA
mkdocs_graph_plugin-1.2.1.post1.dev0.dist-info/WHEEL
mkdocs_graph_plugin-1.2.1.post1.dev0.dist-info/entry_points.txt
mkdocs_graph_plugin-1.2.1.post1.dev0.dist-info/top_level.txt
mkdocs_graph_plugin-1.2.1.post1.dev0.dist-info/RECORD
