Metadata-Version: 2.4
Name: mkdocs-graph-plugin
Version: 1.2.1.post1.dev0
Summary: A MkDocs plugin to generate an interactive graph of your documentation.
Author-email: develmusa <develmusa@users.noreply.github.com>
License: MIT
Project-URL: Homepage, https://github.com/develmusa/mkdocs-graph-plugin
Project-URL: Documentation, https://develmusa.github.io/mkdocs-graph-plugin/
Project-URL: Repository, https://github.com/develmusa/mkdocs-graph-plugin
Project-URL: Issues, https://github.com/develmusa/mkdocs-graph-plugin/issues
Keywords: mkdocs,plugin,graph,documentation
Classifier: Development Status :: 3 - Alpha
Classifier: Intended Audience :: Developers
Classifier: License :: OSI Approved :: MIT License
Classifier: Programming Language :: Python :: 3
Classifier: Programming Language :: Python :: 3.10
Classifier: Programming Language :: Python :: 3.11
Classifier: Programming Language :: Python :: 3.12
Classifier: Programming Language :: Python :: 3.13
Classifier: Topic :: Documentation
Classifier: Topic :: Software Development :: Documentation
Requires-Python: >=3.10
License-File: LICENSE
Requires-Dist: mkdocs-material>=9.0.0
Provides-Extra: dev
Requires-Dist: setuptools-scm; extra == "dev"
Requires-Dist: mkdocs-material; extra == "dev"
Requires-Dist: pytest; extra == "dev"
Requires-Dist: hypothesis; extra == "dev"
Requires-Dist: ruff; extra == "dev"
Requires-Dist: pre-commit; extra == "dev"
Requires-Dist: pyright; extra == "dev"
Requires-Dist: pytest-mock; extra == "dev"
Requires-Dist: nox; extra == "dev"
Requires-Dist: pymdown-extensions; extra == "dev"
Dynamic: license-file
